ety/__init__.py
ety/__main__.py
ety/census.py
ety/cli.py
ety/language.py
ety/tree.py
ety/word.py
ety/data/__init__.py
ety/data/etymologies.json
ety/data/generate.py
ety/data/iso-639-2.json
ety/data/iso-639-3.json
ety-1.4.0.dist-info/LICENSE
ety-1.4.0.dist-info/METADATA
ety-1.4.0.dist-info/WHEEL
ety-1.4.0.dist-info/entry_points.txt
ety-1.4.0.dist-info/top_level.txt
ety-1.4.0.dist-info/RECORD
