Metadata-Version: 2.1
Name: ety
Version: 1.4.0
Summary: discover the etymology of words
Home-page: https://github.com/jmsv/ety-python
Author: James Vickery
Author-email: dev@jmsv.me
Project-URL: Source, https://github.com/jmsv/ety-python
Project-URL: Bug Reports, https://github.com/jmsv/ety-python/issues
Keywords: etymology origins english language words
Classifier: Development Status :: 5 - Production/Stable
Classifier: License :: OSI Approved :: MIT License
Classifier: Programming Language :: Python :: 2
Classifier: Programming Language :: Python :: 2.7
Classifier: Programming Language :: Python :: 3
Classifier: Programming Language :: Python :: 3.4
Classifier: Programming Language :: Python :: 3.5
Classifier: Programming Language :: Python :: 3.6
Classifier: Programming Language :: Python :: 3.7
Classifier: Programming Language :: Python :: 3.8
Classifier: Programming Language :: Python :: 3.9
Classifier: Programming Language :: Python :: 3.10
Requires-Python: >=2.7, !=3.0.*, !=3.1.*, !=3.2.*, <4
License-File: LICENSE
Requires-Dist: treelib
Requires-Dist: colorful
Requires-Dist: six
Provides-Extra: dev
Requires-Dist: flake8 ; extra == 'dev'
